Metadata-Version: 1.1
Name: torchairflow
Version: 0.0.4
Summary: test pkg
Home-page: UNKNOWN
Author: vaishvik24
Author-email: vaishvik@acceldata.io
License: MIT
Keywords: python
Platform: UNKNOWN
Classifier: Development Status :: 5 - Production/Stable
Classifier: Intended Audience :: Education
Classifier: Operating System :: Microsoft :: Windows :: Windows 10
Classifier: License :: OSI Approved :: MIT License
Classifier: Programming Language :: Python :: 3
